[{"DOI": "10.1007/978-3-540-24849-1_14", "ISBN": "978-3-540-24849-1", "abstract": "We set out to study the consequences of the assumption of types of wellfounded trees in dependent type theories. We do so by investigating the categorical notion of wellfounded tree introduced in\u00a0[16]. Our main result shows that wellfounded trees allow us to define initial algebras for a wide class of endofunctors on locally cartesian closed categories.", "author": [{"family": "Gambino", "given": "Nicola"}, {"family": "Hyland", "given": "Martin"}], "container-title": "Types for Proofs and Programs", "editor": [{"family": "Berardi", "given": "Stefano"}, {"family": "Coppo", "given": "Mario"}, {"family": "Damiani", "given": "Ferruccio"}], "id": "gambino_wellfounded_2004", "issued": {"date-parts": [[2004]]}, "keyword": "Forgetful Functor, Left Adjoint, Monoidal Category, Natural Transformation, Type Theory", "page": "210-225", "publisher": "Springer", "publisher-place": "Berlin, Heidelberg", "title": "Wellfounded Trees and Dependent Polynomial Functors", "type": "paper-conference", "original_bibtex": "@inproceedings{gambino_wellfounded_2004,\n title = {Wellfounded {Trees} and {Dependent} {Polynomial} {Functors}},\n author = {Gambino, Nicola and Hyland, Martin},\n year = {2004},\n isbn = {978-3-540-24849-1},\n doi = {10.1007/978-3-540-24849-1_14},\n booktitle = {Types for {Proofs} and {Programs}},\n editor = {Berardi, Stefano and Coppo, Mario and Damiani, Ferruccio},\n pages = {210--225},\n publisher = {Springer},\n address = {Berlin, Heidelberg},\n file = {Full Text PDF:/Users/maxsnew/Zotero/storage/6FMSQHE3/Gambino and Hyland - 2004 - Wellfounded Trees and Dependent Polynomial Functors.pdf:application/pdf},\n keywords = {Forgetful Functor, Left Adjoint, Monoidal Category, Natural Transformation, Type Theory},\n language = {en},\n abstract = {We set out to study the consequences of the assumption of types of wellfounded trees in dependent type theories. We do so by investigating the categorical notion of wellfounded tree introduced in\u00a0[16]. Our main result shows that wellfounded trees allow us to define initial algebras for a wide class of endofunctors on locally cartesian closed categories.}\n}\n"}]